odoo/addons/stock_fleet_delivery_driver/README.rst
odoo/addons/stock_fleet_delivery_driver/__init__.py
odoo/addons/stock_fleet_delivery_driver/__manifest__.py
odoo/addons/stock_fleet_delivery_driver/i18n/es.po
odoo/addons/stock_fleet_delivery_driver/i18n/it.po
odoo/addons/stock_fleet_delivery_driver/i18n/stock_fleet_delivery_driver.pot
odoo/addons/stock_fleet_delivery_driver/models/__init__.py
odoo/addons/stock_fleet_delivery_driver/models/delivery_carrier.py
odoo/addons/stock_fleet_delivery_driver/models/stock_move_line.py
odoo/addons/stock_fleet_delivery_driver/models/stock_picking.py
odoo/addons/stock_fleet_delivery_driver/models/stock_picking_batch.py
odoo/addons/stock_fleet_delivery_driver/models/stock_picking_type.py
odoo/addons/stock_fleet_delivery_driver/readme/CONFIGURE.md
odoo/addons/stock_fleet_delivery_driver/readme/CONTEXT.md
odoo/addons/stock_fleet_delivery_driver/readme/CONTRIBUTORS.md
odoo/addons/stock_fleet_delivery_driver/readme/DESCRIPTION.md
odoo/addons/stock_fleet_delivery_driver/readme/ROADMAP.md
odoo/addons/stock_fleet_delivery_driver/readme/USAGE.md
odoo/addons/stock_fleet_delivery_driver/reports/report_picking_batch.xml
odoo/addons/stock_fleet_delivery_driver/static/description/icon.png
odoo/addons/stock_fleet_delivery_driver/static/description/index.html
odoo/addons/stock_fleet_delivery_driver/tests/__init__.py
odoo/addons/stock_fleet_delivery_driver/tests/test_stock_fleet_delivery_driver.py
odoo/addons/stock_fleet_delivery_driver/views/delivery_carrier_views.xml
odoo/addons/stock_fleet_delivery_driver/views/stock_move_line_views.xml
odoo/addons/stock_fleet_delivery_driver/views/stock_picking_batch_views.xml
odoo/addons/stock_fleet_delivery_driver/views/stock_picking_type_views.xml
odoo/addons/stock_fleet_delivery_driver/views/stock_picking_views.xml
odoo_addon_stock_fleet_delivery_driver-18.0.1.0.1.2.dist-info/METADATA
odoo_addon_stock_fleet_delivery_driver-18.0.1.0.1.2.dist-info/WHEEL
odoo_addon_stock_fleet_delivery_driver-18.0.1.0.1.2.dist-info/top_level.txt
odoo_addon_stock_fleet_delivery_driver-18.0.1.0.1.2.dist-info/RECORD
